crabatar/__init__.py
crabatar/crab.png
crabatar/exceptions.py
crabatar/models.py
crabatar/utils.py
crabatar-1.0.3.dist-info/LICENSE
crabatar-1.0.3.dist-info/METADATA
crabatar-1.0.3.dist-info/WHEEL
crabatar-1.0.3.dist-info/top_level.txt
crabatar-1.0.3.dist-info/RECORD
