Metadata-Version: 2.1
Name: crabatar
Version: 1.0.3
Summary: Generate crab-themed avatars procedurally from usernames.
Home-page: https://github.com/jakeledoux/crabatar
Author: Jake Ledoux
Author-email: contactjakeledoux@gmail.com
License: GNU General Public License v2.0
Platform: UNKNOWN
